{
  "exam": {
    "exam_id": "H29-2",
    "year": 2017,
    "era": "平成",
    "session": 2,
    "subject": "EJU数学"
  },
  "spec_version": "1.4",
  "course": 2,
  "track": "science",
  "question_id": "H29-2-II-1",
  "section": "II",
  "order": 1,
  "type": "fill_in",
  "original_ja": {
    "text": "漸化式 a1=18, an+1−12an+3^{n+2}=0 (n=1,2,3,…) で定まる数列 {an} の一般項を求めよう。数列 {bn} を bn=an/[A]^n と定めると，b1=[B], bn+1−[C]bn+[D]=0 を満たす。この漸化式は bn+1−[E]=[F](bn−[E]) と変形できる。ここで cn=bn−[E] とおくと，{cn} は初項 [G]，公比 [H] の等比数列である。したがって an=[I]^n([J]·[K]^{n−1}+[L]) である。"
  },
  "pattern_id": "REC_LINEAR_SHIFT",
  "structure": {
    "blanks": [
      {
        "id": "A",
        "length": 1,
        "answer": "3"
      },
      {
        "id": "B",
        "length": 1,
        "answer": "6"
      },
      {
        "id": "CD",
        "length": 2,
        "answer": "43"
      },
      {
        "id": "EF",
        "length": 2,
        "answer": "14"
      },
      {
        "id": "G",
        "length": 1,
        "answer": "5"
      },
      {
        "id": "H",
        "length": 1,
        "answer": "4"
      },
      {
        "id": "IJKL",
        "length": 4,
        "answer": "3541"
      }
    ]
  }
}
