{
  "exam": {
    "exam_id": "H25-2",
    "year": 2013,
    "era": "平成",
    "session": 2,
    "subject": "EJU数学"
  },
  "course": 2,
  "track": "science",
  "question_id": "H25-2-II-1",
  "section": "II",
  "order": 1,
  "type": "fill_in",
  "pattern_id": "SEQ_ARITH_GEOSERIES_OPT",
  "original_ja": {
    "text": "数列{a_n}は等差数列で a_2=2, a_6=3a_3 を満たす。級数 \\sum_{n=1}^\\infty \\frac{3^n}{r^{a_n}} を考える（r>0）。(1) 初項をa, 公差をdとすると a=[AB], d=[C]。(2) この級数は初項が [D]r^{[E]}, 公比が [F]/r^{[G]} の無限等比級数である。したがって r>3^{[H]/[I]} のとき収束し，和Sは S=([J]r^{[K]})/(r^{[L]}-[M])。(3) Sが最小となるのは r=[N]^{[O]/2} のときである。"
  },
  "solution": {
    "steps": [
      {
        "idx": 1,
        "description": "等差数列条件から初項と公差を決める。",
        "math": "a_2=a+d=2,\\ a_6=a+5d=3(a+2d)\\Rightarrow d=-2a\\Rightarrow a=-2,d=4"
      },
      {
        "idx": 2,
        "description": "一般項 a_n を用いて級数を等比化。",
        "math": "a_n=a+(n-1)d=4n-6,\\ \\frac{3^n}{r^{a_n}}=\\frac{3^n}{r^{4n-6}}=r^6\\left(\\frac{3}{r^4}\\right)^n"
      },
      {
        "idx": 3,
        "description": "収束条件と和。",
        "math": "\\left|\\frac{3}{r^4}\\right|<1\\Rightarrow r>3^{1/4},\\ S=\\frac{3r^2}{1-3/r^4}=\\frac{3r^6}{r^4-3}"
      },
      {
        "idx": 4,
        "description": "S の最小。",
        "math": "S(r)=\\frac{3r^6}{r^4-3},\\ S'(r)=\\frac{6r^5(r^4-9)}{(r^4-3)^2}=0\\Rightarrow r^4=9\\Rightarrow r=\\sqrt3"
      }
    ]
  },
  "answer_ref": {
    "course": 2,
    "section": "II",
    "q": "Q1",
    "sub": "(1)(2)(3)",
    "group": "AB/C/D/E/F/G/H/I/J/K/L/M/N/O"
  },
  "solution_ref": "solutions/H25-2/course2/H25-2-II-1.zh.md",
  "tagging_status": "ok",
  "structure": {
    "blanks": [
      {
        "id": "AB",
        "length": 2,
        "answer": "-2"
      },
      {
        "id": "C",
        "length": 1,
        "answer": "4"
      },
      {
        "id": "DE",
        "length": 2,
        "answer": "32"
      },
      {
        "id": "FG",
        "length": 2,
        "answer": "34"
      },
      {
        "id": "HI",
        "length": 2,
        "answer": "14"
      },
      {
        "id": "JKLM",
        "length": 4,
        "answer": "3643"
      },
      {
        "id": "NO",
        "length": 2,
        "answer": "31"
      }
    ]
  }
}
